LICENSE.md
MANIFEST.in
README.md
setup.cfg
setup.py
dj_upload2s3/__init__.py
dj_upload2s3/admin.py
dj_upload2s3/apps.py
dj_upload2s3/s3_signature.py
dj_upload2s3.egg-info/PKG-INFO
dj_upload2s3.egg-info/SOURCES.txt
dj_upload2s3.egg-info/dependency_links.txt
dj_upload2s3.egg-info/not-zip-safe
dj_upload2s3.egg-info/top_level.txt
dj_upload2s3/static/dj_upload2s3/css/upload.css
dj_upload2s3/templates/dj_upload2s3/admin_upload.html