Metadata-Version: 1.1
Name: dj-upload2s3
Version: 0.0.3
Summary: Django Direct Upload files to S3
Home-page: https://github.com/Microdisseny/dj_upload2s3
Author: Alexandre Busquets
Author-email: abusquets@gmail.com
License: MIT License
Platform: OS Independent
Classifier: Framework :: Django
Classifier: Intended Audience :: Developers
Classifier: License :: OSI Approved :: MIT License
Classifier: Operating System :: OS Independent
Classifier: Topic :: Software Development
Classifier: Programming Language :: Python
Classifier: Programming Language :: Python :: 3
Classifier: Environment :: Web Environment
Classifier: Development Status :: 4 - Beta
Classifier: Topic :: Software Development :: Libraries :: Python Modules
